overcast/__init__.py
overcast/client.py
overcast/exceptions.py
overcast/logging.py
overcast/worker.py
overcast_py_sdk-1.1.0.dist-info/METADATA
overcast_py_sdk-1.1.0.dist-info/WHEEL
overcast_py_sdk-1.1.0.dist-info/top_level.txt
overcast_py_sdk-1.1.0.dist-info/RECORD
